{
  "version": "v1alpha",
  "servicePath": "",
  "fullyEncodeReservedExpansion": true,
  "description": "",
  "version_module": true,
  "mtlsRootUrl": "https://firebaseappdistribution.mtls.googleapis.com/",
  "schemas": {
    "GoogleFirebaseAppdistroV1alphaJwt": {
      "id": "GoogleFirebaseAppdistroV1alphaJwt",
      "type": "object",
      "properties": {
        "token": {
          "type": "string"
        }
      }
    },
    "GoogleFirebaseAppdistroV1alphaCreateReleaseNotesResponse": {
      "type": "object",
      "properties": {},
      "id": "GoogleFirebaseAppdistroV1alphaCreateReleaseNotesResponse"
    },
    "GoogleFirebaseAppdistroV1ReleaseNotes": {
      "type": "object",
      "properties": {
        "text": {
          "description": "The text of the release notes.",
          "type": "string"
        }
      },
      "description": "Notes that belong to a release.",
      "id": "GoogleFirebaseAppdistroV1ReleaseNotes"
    },
    "GoogleFirebaseAppdistroV1alphaRelease": {
      "description": "Proto defining a release object",
      "properties": {
        "testerCount": {
          "type": "integer",
          "format": "int32",
          "description": "Count of testers added to the release"
        },
        "instanceId": {
          "type": "string",
          "description": "Instance id of the release"
        },
        "receivedAt": {
          "type": "string",
          "description": "unused. ",
          "deprecated": true,
          "format": "google-datetime"
        },
        "distributedAt": {
          "format": "google-datetime",
          "type": "string",
          "description": "Timestamp when the release was created"
        },
        "testerWithInstallCount": {
          "format": "int32",
          "type": "integer",
          "description": "Number of testers who have installed the release"
        },
        "buildVersion": {
          "type": "string",
          "description": "Release build version"
        },
        "openInvitationCount": {
          "description": "Number of testers who have open invitations for the release",
          "format": "int32",
          "type": "integer"
        },
        "lastActivityAt": {
          "type": "string",
          "description": "Last activity timestamp",
          "format": "google-datetime"
        },
        "releaseNotesSummary": {
          "description": "Release notes summary",
          "type": "string"
        },
        "displayVersion": {
          "type": "string",
          "description": "Release version"
        },
        "id": {
          "type": "string",
          "description": "Release Id"
        }
      },
      "id": "GoogleFirebaseAppdistroV1alphaRelease",
      "type": "object"
    },
    "GoogleFirebaseAppdistroV1Release": {
      "properties": {
        "firebaseConsoleUri": {
          "type": "string",
          "description": "Output only. A link to the Firebase console displaying a single release.",
          "readOnly": true
        },
        "testingUri": {
          "readOnly": true,
          "type": "string",
          "description": "Output only. A link to the release in the tester web clip or Android app that lets testers (which were granted access to the app) view release notes and install the app onto their devices."
        },
        "binaryDownloadUri": {
          "readOnly": true,
          "type": "string",
          "description": "Output only. A signed link (which expires in one hour) to directly download the app binary (IPA/APK/AAB) file."
        },
        "releaseNotes": {
          "description": "Notes of the release.",
          "$ref": "GoogleFirebaseAppdistroV1ReleaseNotes"
        },
        "displayVersion": {
          "readOnly": true,
          "type": "string",
          "description": "Output only. Display version of the release. For an Android release, the display version is the `versionName`. For an iOS release, the display version is the `CFBundleShortVersionString`."
        },
        "buildVersion": {
          "description": "Output only. Build version of the release. For an Android release, the build version is the `versionCode`. For an iOS release, the build version is the `CFBundleVersion`.",
          "readOnly": true,
          "type": "string"
        },
        "name": {
          "type": "string",
          "description": "The name of the release resource. Format: `projects/{project_number}/apps/{app_id}/releases/{release_id}`"
        },
        "createTime": {
          "description": "Output only. The time the release was created.",
          "format": "google-datetime",
          "readOnly": true,
          "type": "string"
        }
      },
      "description": "A release of a Firebase app.",
      "type": "object",
      "id": "GoogleFirebaseAppdistroV1Release"
    },
    "GoogleFirebaseAppdistroV1alphaGetUploadStatusResponse": {
      "id": "GoogleFirebaseAppdistroV1alphaGetUploadStatusResponse",
      "type": "object",
      "properties": {
        "release": {
          "description": "The release that was created from the upload (only set on \"SUCCESS\")",
          "$ref": "GoogleFirebaseAppdistroV1alphaRelease"
        },
        "message": {
          "description": "Any additional context for the given upload status (e.g. error message) Meant to be displayed to the client",
          "type": "string"
        },
        "errorCode": {
          "enum": [
            "ERROR_UNSPECIFIED",
            "INVALID_ZIP",
            "MISSING_PLIST",
            "MISSING_PROFILE",
            "VERSION_TOO_LONG",
            "MISSING_UUIDS",
            "MISSING_RESOURCES",
            "MISSING_MANIFEST",
            "IOS_METADATA_ERROR",
            "ANDROID_METADATA_ERROR",
            "UNSUPPORTED_PLATFORM_TYPE",
            "BUNDLE_ID_MISMATCH",
            "APK_NOT_ZIP_ALIGNED",
            "INVALID_CERTIFICATE",
            "APK_TOO_LARGE",
            "AAB_NOT_PUBLISHED",
            "INVALID_PLIST_DEVICE_FAMILIES",
            "AAB_TOS_NOT_ACCEPTED",
            "APP_NAME_TOO_LONG",
            "AAB_DEVELOPER_ACCOUNT_NOT_LINKED",
            "AAB_NO_APP_WITH_GIVEN_PACKAGE_NAME_IN_ACCOUNT",
            "AAB_UPLOAD_ERROR"
          ],
          "enumDescriptions": [
            "",
            "",
            "",
            "",
            "",
            "",
            "",
            "",
            "",
            "",
            "",
            "",
            "",
            "",
            "",
            "",
            "",
            "",
            "",
            "",
            "",
            ""
          ],
          "type": "string",
          "description": "The error code associated with (only set on \"FAILURE\")"
        },
        "status": {
          "enumDescriptions": [
            "",
            "",
            "",
            "",
            ""
          ],
          "type": "string",
          "enum": [
            "STATUS_UNSPECIFIED",
            "IN_PROGRESS",
            "ALREADY_UPLOADED",
            "SUCCESS",
            "ERROR"
          ],
          "description": "The status of the upload"
        }
      }
    },
    "GoogleFirebaseAppdistroV1alphaLoginCredentialFieldHints": {
      "type": "object",
      "id": "GoogleFirebaseAppdistroV1alphaLoginCredentialFieldHints",
      "description": "Hints to the crawler for identifying input fields",
      "properties": {
        "passwordResourceName": {
          "type": "string",
          "description": "Required. The Android resource name of the password UI element. For example, in Java: R.string.foo in xml: @string/foo Only the \"foo\" part is needed. Reference doc: https://developer.android.com/guide/topics/resources/accessing-resources.html"
        },
        "usernameResourceName": {
          "type": "string",
          "description": "Required. The Android resource name of the username UI element. For example, in Java: R.string.foo in xml: @string/foo Only the \"foo\" part is needed. Reference doc: https://developer.android.com/guide/topics/resources/accessing-resources.html"
        }
      }
    },
    "GoogleFirebaseAppdistroV1alphaApp": {
      "properties": {
        "appId": {
          "type": "string",
          "description": "Firebase gmp app id"
        },
        "contactEmail": {
          "type": "string",
          "description": "Developer contact email for testers to reach out to about privacy or support issues."
        },
        "projectNumber": {
          "description": "Project number of the Firebase project, for example 300830567303.",
          "type": "string"
        },
        "aabCertificate": {
          "$ref": "GoogleFirebaseAppdistroV1alphaAabCertificate",
          "description": "App bundle test certificate generated for the app."
        },
        "aabState": {
          "description": "App bundle state. Only valid for android apps. The app_view field in the request must be set to FULL in order for this to be populated.",
          "enumDescriptions": [
            "Aab state unspecified",
            "App can receive app bundle uploads",
            "Firebase project is not linked to a Play developer account",
            "There is no app in linked Play developer account with the same bundle id",
            "The app in Play developer account is not in a published state",
            "Play App status is unavailable",
            "Play IAS terms not accepted"
          ],
          "type": "string",
          "enum": [
            "AAB_STATE_UNSPECIFIED",
            "ACTIVE",
            "PLAY_ACCOUNT_NOT_LINKED",
            "NO_APP_WITH_GIVEN_BUNDLE_ID_IN_PLAY_ACCOUNT",
            "APP_NOT_PUBLISHED",
            "AAB_STATE_UNAVAILABLE",
            "PLAY_IAS_TERMS_NOT_ACCEPTED"
          ]
        },
        "platform": {
          "description": "iOS or Android",
          "type": "string"
        },
        "bundleId": {
          "description": "Bundle identifier",
          "type": "string"
        }
      },
      "id": "GoogleFirebaseAppdistroV1alphaApp",
      "type": "object"
    },
    "GoogleFirebaseAppdistroV1alphaReleaseTest": {
      "id": "GoogleFirebaseAppdistroV1alphaReleaseTest",
      "properties": {
        "createTime": {
          "type": "string",
          "format": "google-datetime",
          "description": "Output only. Timestamp when the test was run.",
          "readOnly": true
        },
        "loginCredential": {
          "description": "Optional. Input only. Login credentials for the test. Input only.",
          "$ref": "GoogleFirebaseAppdistroV1alphaLoginCredential"
        },
        "name": {
          "description": "The name of the release test resource. Format: `projects/{project_number}/apps/{app_id}/releases/{release_id}/tests/{test_id}`",
          "type": "string"
        },
        "deviceExecutions": {
          "items": {
            "$ref": "GoogleFirebaseAppdistroV1alphaDeviceExecution"
          },
          "type": "array",
          "description": "Required. The results of the test on each device."
        },
        "aiInstructions": {
          "$ref": "GoogleFirebaseAppdistroV1alphaAiInstructions",
          "description": "Optional. Input only. Instructions for AI driven test. Input only."
        }
      },
      "description": "The results of running an automated test on a release.",
      "type": "object"
    },
    "GoogleFirebaseAppdistroV1alphaRoboCrawler": {
      "description": "Configuration for Robo crawler",
      "properties": {
        "aiInstructions": {
          "$ref": "GoogleFirebaseAppdistroV1alphaAiInstructions",
          "description": "Optional. Instructions for AI driven test"
        },
        "loginCredential": {
          "description": "Optional. Login credential for automated tests",
          "$ref": "GoogleFirebaseAppdistroV1alphaLoginCredential"
        }
      },
      "type": "object",
      "id": "GoogleFirebaseAppdistroV1alphaRoboCrawler"
    },
    "GoogleFirebaseAppdistroV1alphaAppCrash": {
      "id": "GoogleFirebaseAppdistroV1alphaAppCrash",
      "properties": {
        "stackTrace": {
          "type": "string",
          "readOnly": true,
          "description": "Output only. The raw stack trace."
        },
        "message": {
          "type": "string",
          "readOnly": true,
          "description": "Output only. The message associated with the crash."
        }
      },
      "type": "object",
      "description": "An app crash that occurred during an automated test."
    },
    "GoogleFirebaseAppdistroV1alphaAiInstructions": {
      "type": "object",
      "id": "GoogleFirebaseAppdistroV1alphaAiInstructions",
      "properties": {
        "appDescription": {
          "description": "Optional. Describes the app to give the AI some context",
          "type": "string"
        },
        "steps": {
          "items": {
            "$ref": "GoogleFirebaseAppdistroV1alphaAiInstructionsStep"
          },
          "description": "Required. Steps to be accomplished by the AI",
          "type": "array"
        }
      },
      "description": "Instructions for AI driven test"
    },
    "GoogleFirebaseAppdistroV1UploadReleaseMetadata": {
      "description": "Operation metadata for `UploadRelease`.",
      "type": "object",
      "properties": {},
      "id": "GoogleFirebaseAppdistroV1UploadReleaseMetadata"
    },
    "GoogleFirebaseAppdistroV1alphaGetTesterUdidsResponse": {
      "properties": {
        "testerUdids": {
          "type": "array",
          "items": {
            "$ref": "GoogleFirebaseAppdistroV1alphaTesterUdid"
          },
          "description": "The UDIDs of tester iOS devices in a project"
        }
      },
      "type": "object",
      "id": "GoogleFirebaseAppdistroV1alphaGetTesterUdidsResponse",
      "description": "Response containing the UDIDs of tester iOS devices in a project"
    },
    "GoogleFirebaseAppdistroV1alphaRoboStats": {
      "properties": {
        "crawlDuration": {
          "readOnly": true,
          "description": "Output only. Duration of crawl.",
          "type": "string",
          "format": "google-duration"
        },
        "mainActivityCrawlTimedOut": {
          "type": "boolean",
          "readOnly": true,
          "description": "Output only. Whether the main activity crawl timed out."
        },
        "distinctVisitedScreens": {
          "description": "Output only. Number of distinct screens visited.",
          "type": "integer",
          "readOnly": true,
          "format": "int32"
        },
        "actionsPerformed": {
          "description": "Output only. Number of actions that crawler performed.",
          "readOnly": true,
          "type": "integer",
          "format": "int32"
        }
      },
      "description": "Statistics collected during a Robo test.",
      "id": "GoogleFirebaseAppdistroV1alphaRoboStats",
      "type": "object"
    },
    "GoogleFirebaseAppdistroV1alphaTesterUdid": {
      "id": "GoogleFirebaseAppdistroV1alphaTesterUdid",
      "description": "The UDIDs of a tester's iOS device",
      "type": "object",
      "properties": {
        "platform": {
          "description": "The platform of the tester's device",
          "type": "string"
        },
        "udid": {
          "type": "string",
          "description": "The UDID of the tester's device"
        },
        "name": {
          "description": "The name of the tester's device",
          "type": "string"
        }
      }
    },
    "GoogleFirebaseAppdistroV1alphaDeviceExecution": {
      "description": "The results of running an automated test on a particular device.",
      "type": "object",
      "id": "GoogleFirebaseAppdistroV1alphaDeviceExecution",
      "properties": {
        "inconclusiveReason": {
          "description": "Output only. The reason why the test was inconclusive.",
          "type": "string",
          "readOnly": true,
          "enum": [
            "INCONCLUSIVE_REASON_UNSPECIFIED",
            "QUOTA_EXCEEDED",
            "INFRASTRUCTURE_FAILURE",
            "SERVICE_NOT_ACTIVATED",
            "NO_SIGNATURE",
            "NO_LAUNCHER_ACTIVITY",
            "FORBIDDEN_PERMISSIONS",
            "DEVICE_ADMIN_RECEIVER",
            "NO_CODE_APK",
            "INVALID_APK_PREVIEW_SDK"
          ],
          "enumDescriptions": [
            "Reason unspecified.",
            "Not enough quota remained to run the test.",
            "The outcome of the test could not be determined because of a failure in the test running infrastructure.",
            "A required cloud service api is not activated (Google Cloud Testing API or Cloud Tool Results API).",
            "The app was not signed.",
            "A main launcher activity could not be found.",
            "The app declares one or more permissions that are not allowed.",
            "Device administrator applications are not allowed.",
            "APK contains no code. See also https://developer.android.com/guide/topics/manifest/application-element.html#code",
            "APK is built for a preview SDK which is unsupported."
          ]
        },
        "roboStats": {
          "readOnly": true,
          "description": "Output only. The statistics collected during the Robo test.",
          "$ref": "GoogleFirebaseAppdistroV1alphaRoboStats"
        },
        "appCrash": {
          "$ref": "GoogleFirebaseAppdistroV1alphaAppCrash",
          "description": "Output only. An app crash, if any occurred during the test.",
          "readOnly": true
        },
        "videoUri": {
          "description": "Output only. A URI to a video of the test run.",
          "readOnly": true,
          "type": "string"
        },
        "screenshotUris": {
          "type": "array",
          "items": {
            "type": "string"
          },
          "description": "Output only. A list of screenshot image URIs taken from the Robo crawl. The file names are numbered by the order in which they were taken.",
          "readOnly": true
        },
        "failedReason": {
          "enumDescriptions": [
            "Reason unspecified.",
            "The app crashed during the test.",
            "If an app is not installed and thus no test can be run with the app. This might be caused by trying to run a test on an unsupported platform.",
            "If the app could not be crawled (possibly because the app did not start).",
            "If the device ran out of memory during the test."
          ],
          "readOnly": true,
          "type": "string",
          "enum": [
            "FAILED_REASON_UNSPECIFIED",
            "CRASHED",
            "NOT_INSTALLED",
            "UNABLE_TO_CRAWL",
            "DEVICE_OUT_OF_MEMORY"
          ],
          "description": "Output only. The reason why the test failed."
        },
        "resultsStoragePath": {
          "description": "Output only. The path to a directory in Cloud Storage that will eventually contain the results for this execution. For example, gs://bucket/Nexus5-18-en-portrait.",
          "type": "string",
          "readOnly": true
        },
        "device": {
          "description": "Required. The device that the test was run on.",
          "$ref": "GoogleFirebaseAppdistroV1alphaTestDevice"
        },
        "state": {
          "description": "Output only. The state of the test.",
          "enumDescriptions": [
            "Test state unspecified.",
            "The test is in progress.",
            "The test has passed.",
            "The test has failed.",
            "The test was inconclusive."
          ],
          "type": "string",
          "readOnly": true,
          "enum": [
            "TEST_STATE_UNSPECIFIED",
            "IN_PROGRESS",
            "PASSED",
            "FAILED",
            "INCONCLUSIVE"
          ]
        },
        "crawlGraphUri": {
          "description": "Output only. A URI to an image of the Robo crawl graph.",
          "readOnly": true,
          "type": "string"
        }
      }
    },
    "GoogleFirebaseAppdistroV1alphaCreateReleaseNotesRequest": {
      "type": "object",
      "properties": {
        "releaseNotes": {
          "$ref": "GoogleFirebaseAppdistroV1alphaReleaseNotes",
          "description": "The actual release notes body from the user"
        }
      },
      "id": "GoogleFirebaseAppdistroV1alphaCreateReleaseNotesRequest"
    },
    "GoogleFirebaseAppdistroV1alphaAiInstructionsStep": {
      "id": "GoogleFirebaseAppdistroV1alphaAiInstructionsStep",
      "type": "object",
      "description": "A step to be accomplished by the AI",
      "properties": {
        "goal": {
          "description": "A goal to be accomplished by the AI",
          "type": "string"
        },
        "assertion": {
          "description": "An assertion to be checked by the AI",
          "type": "string"
        }
      }
    },
    "GoogleFirebaseAppdistroV1alphaLoginCredential": {
      "properties": {
        "username": {
          "description": "Optional. Username for automated tests",
          "type": "string"
        },
        "password": {
          "description": "Optional. Password for automated tests",
          "type": "string"
        },
        "google": {
          "description": "Optional. Are these credentials for Google?",
          "type": "boolean"
        },
        "fieldHints": {
          "$ref": "GoogleFirebaseAppdistroV1alphaLoginCredentialFieldHints",
          "description": "Optional. Hints to the crawler for identifying input fields"
        }
      },
      "description": "Login credential for automated tests",
      "id": "GoogleFirebaseAppdistroV1alphaLoginCredential",
      "type": "object"
    },
    "GoogleFirebaseAppdistroV1alphaTestConfig": {
      "type": "object",
      "properties": {
        "roboCrawler": {
          "$ref": "GoogleFirebaseAppdistroV1alphaRoboCrawler",
          "description": "Optional. Configuration for Robo crawler"
        },
        "name": {
          "description": "Identifier. The name of the test configuration resource. Format: `projects/{project_number}/apps/{app_id}/testConfig`",
          "type": "string"
        },
        "testDevices": {
          "items": {
            "$ref": "GoogleFirebaseAppdistroV1alphaTestDevice"
          },
          "description": "Optional. Tests will be run on this list of devices",
          "type": "array"
        }
      },
      "id": "GoogleFirebaseAppdistroV1alphaTestConfig",
      "description": "Configuration for automated tests"
    },
    "GoogleFirebaseAppdistroV1alphaEnableAccessOnReleaseResponse": {
      "id": "GoogleFirebaseAppdistroV1alphaEnableAccessOnReleaseResponse",
      "type": "object",
      "properties": {}
    },
    "GoogleFirebaseAppdistroV1alphaTestDevice": {
      "type": "object",
      "id": "GoogleFirebaseAppdistroV1alphaTestDevice",
      "properties": {
        "locale": {
          "description": "Optional. The locale of the device (e.g. \"en_US\" for US English) during the test.",
          "type": "string"
        },
        "model": {
          "type": "string",
          "description": "Required. The device model."
        },
        "orientation": {
          "type": "string",
          "description": "Optional. The orientation of the device during the test."
        },
        "version": {
          "description": "Required. The version of the device (API level on Android).",
          "type": "string"
        }
      },
      "description": "A device on which automated tests can be run."
    },
    "GoogleFirebaseAppdistroV1alphaReleaseNotes": {
      "id": "GoogleFirebaseAppdistroV1alphaReleaseNotes",
      "type": "object",
      "properties": {
        "releaseNotes": {
          "type": "string"
        }
      }
    },
    "GoogleFirebaseAppdistroV1UploadReleaseResponse": {
      "properties": {
        "result": {
          "enum": [
            "UPLOAD_RELEASE_RESULT_UNSPECIFIED",
            "RELEASE_CREATED",
            "RELEASE_UPDATED",
            "RELEASE_UNMODIFIED"
          ],
          "type": "string",
          "enumDescriptions": [
            "Upload binary result unspecified",
            "Upload binary resulted in a new release",
            "Upload binary updated an existing release",
            "Upload binary resulted in a no-op. A release with the exact same binary already exists."
          ],
          "description": "Result of upload release."
        },
        "release": {
          "description": "Release associated with the uploaded binary.",
          "$ref": "GoogleFirebaseAppdistroV1Release"
        }
      },
      "description": "Response message for `UploadRelease`.",
      "type": "object",
      "id": "GoogleFirebaseAppdistroV1UploadReleaseResponse"
    },
    "GoogleFirebaseAppdistroV1alphaListReleaseTestsResponse": {
      "properties": {
        "nextPageToken": {
          "type": "string",
          "description": "A short-lived token, which can be sent as `pageToken` to retrieve the next page. If this field is omitted, there are no subsequent pages."
        },
        "releaseTests": {
          "description": "The tests listed.",
          "items": {
            "$ref": "GoogleFirebaseAppdistroV1alphaReleaseTest"
          },
          "type": "array"
        }
      },
      "description": "The response message for `ListReleaseTests`.",
      "id": "GoogleFirebaseAppdistroV1alphaListReleaseTestsResponse",
      "type": "object"
    },
    "GoogleFirebaseAppdistroV1alphaGetReleaseByUploadHashResponse": {
      "id": "GoogleFirebaseAppdistroV1alphaGetReleaseByUploadHashResponse",
      "type": "object",
      "properties": {
        "release": {
          "description": "Release object",
          "$ref": "GoogleFirebaseAppdistroV1alphaRelease"
        }
      },
      "description": "Response object to get the release given a upload hash"
    },
    "GoogleFirebaseAppdistroV1alphaProvisionAppResponse": {
      "properties": {},
      "type": "object",
      "id": "GoogleFirebaseAppdistroV1alphaProvisionAppResponse"
    },
    "GoogleFirebaseAppdistroV1alphaEnableAccessOnReleaseRequest": {
      "type": "object",
      "id": "GoogleFirebaseAppdistroV1alphaEnableAccessOnReleaseRequest",
      "properties": {
        "buildVersion": {
          "description": "Optional. Ignored. Used to be build version of the app release if an instance identifier was provided for the release_id.",
          "type": "string",
          "deprecated": true
        },
        "displayVersion": {
          "deprecated": true,
          "description": "Optional. Ignored. Used to be display version of the app release if an instance identifier was provided for the release_id.",
          "type": "string"
        },
        "emails": {
          "type": "array",
          "description": "Optional. An email address which should get access to this release, for example rebeccahe@google.com",
          "items": {
            "type": "string"
          }
        },
        "groupIds": {
          "description": "Optional. A repeated list of group aliases to enable access to a release for Note: This field is misnamed, but can't be changed because we need to maintain compatibility with old build tools",
          "type": "array",
          "items": {
            "type": "string"
          }
        }
      }
    },
    "GoogleFirebaseAppdistroV1alphaAabCertificate": {
      "type": "object",
      "description": "App bundle test certificate",
      "id": "GoogleFirebaseAppdistroV1alphaAabCertificate",
      "properties": {
        "certificateHashMd5": {
          "description": "MD5 hash of the certificate used to resign the AAB",
          "type": "string"
        },
        "certificateHashSha256": {
          "description": "SHA256 hash of the certificate used to resign the AAB",
          "type": "string"
        },
        "certificateHashSha1": {
          "description": "SHA1 hash of the certificate used to resign the AAB",
          "type": "string"
        }
      }
    }
  },
  "auth": {
    "oauth2": {
      "scopes": {
        "https://www.googleapis.com/auth/cloud-platform": {
          "description": "See, edit, configure, and delete your Google Cloud data and see the email address for your Google Account."
        }
      }
    }
  },
  "ownerName": "Google",
  "rootUrl": "https://firebaseappdistribution.googleapis.com/",
  "documentationLink": "https://firebase.google.com/products/app-distribution",
  "name": "firebaseappdistribution",
  "kind": "discovery#restDescription",
  "icons": {
    "x32": "http://www.google.com/images/icons/product/search-32.gif",
    "x16": "http://www.google.com/images/icons/product/search-16.gif"
  },
  "revision": "20240627",
  "discoveryVersion": "v1",
  "ownerDomain": "google.com",
  "canonicalName": "Firebase App Distribution",
  "resources": {
    "projects": {
      "resources": {
        "testers": {
          "methods": {
            "getUdids": {
              "path": "v1alpha/{+project}/testers:udids",
              "flatPath": "v1alpha/projects/{projectsId}/testers:udids",
              "id": "firebaseappdistribution.projects.testers.getUdids",
              "scopes": [
                "https://www.googleapis.com/auth/cloud-platform"
              ],
              "parameterOrder": [
                "project"
              ],
              "response": {
                "$ref": "GoogleFirebaseAppdistroV1alphaGetTesterUdidsResponse"
              },
              "description": "Get UDIDs of tester iOS devices in a project",
              "parameters": {
                "project": {
                  "description": "The name of the project, which is the parent of testers Format: `projects/{project_number}`",
                  "required": true,
                  "pattern": "^projects/[^/]+$",
                  "type": "string",
                  "location": "path"
                },
                "mobilesdkAppId": {
                  "location": "query",
                  "description": "Unique id for a Firebase app of the format: {version}:{project_number}:{platform}:{hash(bundle_id)} Example: 1:581234567376:android:aa0a3c7b135e90289",
                  "type": "string"
                }
              },
              "httpMethod": "GET"
            }
          }
        },
        "apps": {
          "methods": {
            "getTestConfig": {
              "flatPath": "v1alpha/projects/{projectsId}/apps/{appsId}/testConfig",
              "parameters": {
                "name": {
                  "pattern": "^projects/[^/]+/apps/[^/]+/testConfig$",
                  "required": true,
                  "description": "Required. The name of the `TestConfig` resource to retrieve. Format: `projects/{project_number}/apps/{app_id}/testConfig`",
                  "type": "string",
                  "location": "path"
                }
              },
              "httpMethod": "GET",
              "parameterOrder": [
                "name"
              ],
              "id": "firebaseappdistribution.projects.apps.getTestConfig",
              "response": {
                "$ref": "GoogleFirebaseAppdistroV1alphaTestConfig"
              },
              "description": "Gets configuration for automated tests.",
              "scopes": [
                "https://www.googleapis.com/auth/cloud-platform"
              ],
              "path": "v1alpha/{+name}"
            },
            "updateTestConfig": {
              "flatPath": "v1alpha/projects/{projectsId}/apps/{appsId}/testConfig",
              "parameterOrder": [
                "name"
              ],
              "response": {
                "$ref": "GoogleFirebaseAppdistroV1alphaTestConfig"
              },
              "id": "firebaseappdistribution.projects.apps.updateTestConfig",
              "request": {
                "$ref": "GoogleFirebaseAppdistroV1alphaTestConfig"
              },
              "scopes": [
                "https://www.googleapis.com/auth/cloud-platform"
              ],
              "httpMethod": "PATCH",
              "path": "v1alpha/{+name}",
              "description": "Updates a release.",
              "parameters": {
                "name": {
                  "type": "string",
                  "pattern": "^projects/[^/]+/apps/[^/]+/testConfig$",
                  "required": true,
                  "location": "path",
                  "description": "Identifier. The name of the test configuration resource. Format: `projects/{project_number}/apps/{app_id}/testConfig`"
                },
                "updateMask": {
                  "format": "google-fieldmask",
                  "description": "Optional. The list of fields to update.",
                  "type": "string",
                  "location": "query"
                }
              }
            }
          },
          "resources": {
            "releases": {
              "resources": {
                "tests": {
                  "methods": {
                    "list": {
                      "description": "List results for automated tests run on release.",
                      "parameters": {
                        "parent": {
                          "pattern": "^projects/[^/]+/apps/[^/]+/releases/[^/]+$",
                          "type": "string",
                          "location": "path",
                          "description": "Required. The name of the release resource, which is the parent of the tests Format: `projects/{project_number}/apps/{app_id}/releases/{release_id}`",
                          "required": true
                        },
                        "pageSize": {
                          "location": "query",
                          "type": "integer",
                          "format": "int32",
                          "description": "Optional. The maximum number of tests to return. The service may return fewer than this value."
                        },
                        "pageToken": {
                          "type": "string",
                          "location": "query",
                          "description": "Optional. A page token, received from a previous `ListReleaseTests` call. Provide this to retrieve the subsequent page."
                        }
                      },
                      "parameterOrder": [
                        "parent"
                      ],
                      "flatPath": "v1alpha/projects/{projectsId}/apps/{appsId}/releases/{releasesId}/tests",
                      "httpMethod": "GET",
                      "response": {
                        "$ref": "GoogleFirebaseAppdistroV1alphaListReleaseTestsResponse"
                      },
                      "path": "v1alpha/{+parent}/tests",
                      "scopes": [
                        "https://www.googleapis.com/auth/cloud-platform"
                      ],
                      "id": "firebaseappdistribution.projects.apps.releases.tests.list"
                    },
                    "get": {
                      "parameterOrder": [
                        "name"
                      ],
                      "parameters": {
                        "name": {
                          "pattern": "^projects/[^/]+/apps/[^/]+/releases/[^/]+/tests/[^/]+$",
                          "description": "Required. The name of the release test resource. Format: `projects/{project_number}/apps/{app_id}/releases/{release_id}/tests/{test_id}`",
                          "location": "path",
                          "type": "string",
                          "required": true
                        }
                      },
                      "httpMethod": "GET",
                      "path": "v1alpha/{+name}",
                      "scopes": [
                        "https://www.googleapis.com/auth/cloud-platform"
                      ],
                      "id": "firebaseappdistribution.projects.apps.releases.tests.get",
                      "response": {
                        "$ref": "GoogleFirebaseAppdistroV1alphaReleaseTest"
                      },
                      "description": "Get results for automated test run on release.",
                      "flatPath": "v1alpha/projects/{projectsId}/apps/{appsId}/releases/{releasesId}/tests/{testsId}"
                    },
                    "create": {
                      "httpMethod": "POST",
                      "request": {
                        "$ref": "GoogleFirebaseAppdistroV1alphaReleaseTest"
                      },
                      "parameters": {
                        "releaseTestId": {
                          "type": "string",
                          "location": "query",
                          "description": "Optional. The ID to use for the test, which will become the final component of the tests's resource name. This value should be 4-63 characters, and valid characters are /a-z-/. If it is not provided one will be automatically generated."
                        },
                        "parent": {
                          "pattern": "^projects/[^/]+/apps/[^/]+/releases/[^/]+$",
                          "type": "string",
                          "description": "Required. The name of the release resource, which is the parent of the test Format: `projects/{project_number}/apps/{app_id}/releases/{release_id}`",
                          "required": true,
                          "location": "path"
                        }
                      },
                      "description": "Run automated test(s) on release.",
                      "id": "firebaseappdistribution.projects.apps.releases.tests.create",
                      "response": {
                        "$ref": "GoogleFirebaseAppdistroV1alphaReleaseTest"
                      },
                      "path": "v1alpha/{+parent}/tests",
                      "flatPath": "v1alpha/projects/{projectsId}/apps/{appsId}/releases/{releasesId}/tests",
                      "parameterOrder": [
                        "parent"
                      ],
                      "scopes": [
                        "https://www.googleapis.com/auth/cloud-platform"
                      ]
                    }
                  }
                }
              }
            }
          }
        }
      }
    },
    "apps": {
      "resources": {
        "upload_status": {
          "methods": {
            "get": {
              "parameters": {
                "mobilesdkAppId": {
                  "location": "path",
                  "required": true,
                  "description": "Unique id for a Firebase app of the format: {version}:{project_number}:{platform}:{hash(bundle_id)} Example: 1:581234567376:android:aa0a3c7b135e90289",
                  "type": "string"
                },
                "uploadToken": {
                  "location": "path",
                  "type": "string",
                  "required": true,
                  "description": "The token for the upload"
                }
              },
              "flatPath": "v1alpha/apps/{mobilesdkAppId}/upload_status/{uploadToken}",
              "scopes": [
                "https://www.googleapis.com/auth/cloud-platform"
              ],
              "path": "v1alpha/apps/{mobilesdkAppId}/upload_status/{uploadToken}",
              "description": "GET Binary upload status by token",
              "httpMethod": "GET",
              "id": "firebaseappdistribution.apps.upload_status.get",
              "response": {
                "$ref": "GoogleFirebaseAppdistroV1alphaGetUploadStatusResponse"
              },
              "parameterOrder": [
                "mobilesdkAppId",
                "uploadToken"
              ]
            }
          }
        },
        "release_by_hash": {
          "methods": {
            "get": {
              "description": "GET Release by binary upload hash",
              "scopes": [
                "https://www.googleapis.com/auth/cloud-platform"
              ],
              "httpMethod": "GET",
              "parameters": {
                "uploadHash": {
                  "location": "path",
                  "description": "The hash for the upload",
                  "required": true,
                  "type": "string"
                },
                "mobilesdkAppId": {
                  "type": "string",
                  "description": "Unique id for a Firebase app of the format: {version}:{project_number}:{platform}:{hash(bundle_id)} Example: 1:581234567376:android:aa0a3c7b135e90289",
                  "location": "path",
                  "required": true
                }
              },
              "path": "v1alpha/apps/{mobilesdkAppId}/release_by_hash/{uploadHash}",
              "response": {
                "$ref": "GoogleFirebaseAppdistroV1alphaGetReleaseByUploadHashResponse"
              },
              "flatPath": "v1alpha/apps/{mobilesdkAppId}/release_by_hash/{uploadHash}",
              "parameterOrder": [
                "mobilesdkAppId",
                "uploadHash"
              ],
              "id": "firebaseappdistribution.apps.release_by_hash.get"
            }
          }
        },
        "releases": {
          "resources": {
            "notes": {
              "methods": {
                "create": {
                  "flatPath": "v1alpha/apps/{mobilesdkAppId}/releases/{releaseId}/notes",
                  "parameterOrder": [
                    "mobilesdkAppId",
                    "releaseId"
                  ],
                  "httpMethod": "POST",
                  "id": "firebaseappdistribution.apps.releases.notes.create",
                  "scopes": [
                    "https://www.googleapis.com/auth/cloud-platform"
                  ],
                  "parameters": {
                    "releaseId": {
                      "type": "string",
                      "required": true,
                      "location": "path",
                      "description": "Release identifier"
                    },
                    "mobilesdkAppId": {
                      "type": "string",
                      "description": "Unique id for a Firebase app of the format: {version}:{project_number}:{platform}:{hash(bundle_id)} Example: 1:581234567376:android:aa0a3c7b135e90289",
                      "required": true,
                      "location": "path"
                    }
                  },
                  "path": "v1alpha/apps/{mobilesdkAppId}/releases/{releaseId}/notes",
                  "response": {
                    "$ref": "GoogleFirebaseAppdistroV1alphaCreateReleaseNotesResponse"
                  },
                  "request": {
                    "$ref": "GoogleFirebaseAppdistroV1alphaCreateReleaseNotesRequest"
                  },
                  "description": "Create release notes on a release."
                }
              }
            }
          },
          "methods": {
            "enable_access": {
              "parameterOrder": [
                "mobilesdkAppId",
                "releaseId"
              ],
              "parameters": {
                "releaseId": {
                  "location": "path",
                  "required": true,
                  "type": "string",
                  "description": "Release identifier"
                },
                "mobilesdkAppId": {
                  "required": true,
                  "description": "Unique id for a Firebase app of the format: {version}:{project_number}:{platform}:{hash(bundle_id)} Example: 1:581234567376:android:aa0a3c7b135e90289",
                  "location": "path",
                  "type": "string"
                }
              },
              "httpMethod": "POST",
              "path": "v1alpha/apps/{mobilesdkAppId}/releases/{releaseId}/enable_access",
              "request": {
                "$ref": "GoogleFirebaseAppdistroV1alphaEnableAccessOnReleaseRequest"
              },
              "description": "Enable access on a release for testers.",
              "id": "firebaseappdistribution.apps.releases.enable_access",
              "response": {
                "$ref": "GoogleFirebaseAppdistroV1alphaEnableAccessOnReleaseResponse"
              },
              "scopes": [
                "https://www.googleapis.com/auth/cloud-platform"
              ],
              "flatPath": "v1alpha/apps/{mobilesdkAppId}/releases/{releaseId}/enable_access"
            }
          }
        },
        "testers": {
          "methods": {
            "getTesterUdids": {
              "parameters": {
                "project": {
                  "type": "string",
                  "description": "The name of the project, which is the parent of testers Format: `projects/{project_number}`",
                  "location": "query"
                },
                "mobilesdkAppId": {
                  "required": true,
                  "type": "string",
                  "description": "Unique id for a Firebase app of the format: {version}:{project_number}:{platform}:{hash(bundle_id)} Example: 1:581234567376:android:aa0a3c7b135e90289",
                  "location": "path"
                }
              },
              "httpMethod": "GET",
              "response": {
                "$ref": "GoogleFirebaseAppdistroV1alphaGetTesterUdidsResponse"
              },
              "parameterOrder": [
                "mobilesdkAppId"
              ],
              "scopes": [
                "https://www.googleapis.com/auth/cloud-platform"
              ],
              "path": "v1alpha/apps/{mobilesdkAppId}/testers:getTesterUdids",
              "flatPath": "v1alpha/apps/{mobilesdkAppId}/testers:getTesterUdids",
              "id": "firebaseappdistribution.apps.testers.getTesterUdids",
              "description": "Get UDIDs of tester iOS devices in a project"
            }
          }
        }
      },
      "methods": {
        "provisionApp": {
          "description": "Provision app distribution for an existing Firebase app, enabling it to subsequently be used by appdistro.",
          "id": "firebaseappdistribution.apps.provisionApp",
          "response": {
            "$ref": "GoogleFirebaseAppdistroV1alphaProvisionAppResponse"
          },
          "path": "v1alpha/apps/{mobilesdkAppId}",
          "flatPath": "v1alpha/apps/{mobilesdkAppId}",
          "scopes": [
            "https://www.googleapis.com/auth/cloud-platform"
          ],
          "parameters": {
            "mobilesdkAppId": {
              "required": true,
              "type": "string",
              "description": "Unique id for a Firebase app of the format: {version}:{project_number}:{platform}:{hash(bundle_id)} Example: 1:581234567376:android:aa0a3c7b135e90289",
              "location": "path"
            }
          },
          "parameterOrder": [
            "mobilesdkAppId"
          ],
          "httpMethod": "POST"
        },
        "get": {
          "description": "Get the app, if it exists",
          "parameters": {
            "appView": {
              "enumDescriptions": [
                "The default / unset value. The API will default to the BASIC view.",
                "Include everything except aab_state.",
                "Include everything."
              ],
              "location": "query",
              "enum": [
                "APP_VIEW_UNSPECIFIED",
                "BASIC",
                "FULL"
              ],
              "type": "string",
              "description": "App view. When unset or set to BASIC, returns an App with everything set except for aab_state. When set to FULL, returns an App with aab_state set."
            },
            "mobilesdkAppId": {
              "type": "string",
              "description": "Unique id for a Firebase app of the format: {version}:{project_number}:{platform}:{hash(bundle_id)} Example: 1:581234567376:android:aa0a3c7b135e90289",
              "location": "path",
              "required": true
            }
          },
          "parameterOrder": [
            "mobilesdkAppId"
          ],
          "id": "firebaseappdistribution.apps.get",
          "scopes": [
            "https://www.googleapis.com/auth/cloud-platform"
          ],
          "path": "v1alpha/apps/{mobilesdkAppId}",
          "response": {
            "$ref": "GoogleFirebaseAppdistroV1alphaApp"
          },
          "httpMethod": "GET",
          "flatPath": "v1alpha/apps/{mobilesdkAppId}"
        },
        "getJwt": {
          "description": "Get a JWT token",
          "flatPath": "v1alpha/apps/{mobilesdkAppId}/jwt",
          "response": {
            "$ref": "GoogleFirebaseAppdistroV1alphaJwt"
          },
          "path": "v1alpha/apps/{mobilesdkAppId}/jwt",
          "parameterOrder": [
            "mobilesdkAppId"
          ],
          "scopes": [
            "https://www.googleapis.com/auth/cloud-platform"
          ],
          "id": "firebaseappdistribution.apps.getJwt",
          "parameters": {
            "mobilesdkAppId": {
              "type": "string",
              "required": true,
              "description": "Unique id for a Firebase app of the format: {version}:{project_number}:{platform}:{hash(bundle_id)} Example: 1:581234567376:android:aa0a3c7b135e90289",
              "location": "path"
            }
          },
          "httpMethod": "GET"
        }
      }
    }
  },
  "batchPath": "batch",
  "baseUrl": "https://firebaseappdistribution.googleapis.com/",
  "title": "Firebase App Distribution API",
  "parameters": {
    "upload_protocol": {
      "location": "query",
      "description": "Upload protocol for media (e.g. \"raw\", \"multipart\").",
      "type": "string"
    },
    "callback": {
      "type": "string",
      "location": "query",
      "description": "JSONP"
    },
    "prettyPrint": {
      "description": "Returns response with indentations and line breaks.",
      "type": "boolean",
      "default": "true",
      "location": "query"
    },
    "access_token": {
      "location": "query",
      "description": "OAuth access token.",
      "type": "string"
    },
    "$.xgafv": {
      "enum": [
        "1",
        "2"
      ],
      "enumDescriptions": [
        "v1 error format",
        "v2 error format"
      ],
      "description": "V1 error format.",
      "location": "query",
      "type": "string"
    },
    "oauth_token": {
      "type": "string",
      "location": "query",
      "description": "OAuth 2.0 token for the current user."
    },
    "uploadType": {
      "type": "string",
      "location": "query",
      "description": "Legacy upload protocol for media (e.g. \"media\", \"multipart\")."
    },
    "key": {
      "location": "query",
      "description": "API key. Your API key identifies your project and provides you with API access, quota, and reports. Required unless you provide an OAuth 2.0 token.",
      "type": "string"
    },
    "fields": {
      "description": "Selector specifying which fields to include in a partial response.",
      "location": "query",
      "type": "string"
    },
    "alt": {
      "enumDescriptions": [
        "Responses with Content-Type of application/json",
        "Media download with context-dependent Content-Type",
        "Responses with Content-Type of application/x-protobuf"
      ],
      "enum": [
        "json",
        "media",
        "proto"
      ],
      "location": "query",
      "type": "string",
      "default": "json",
      "description": "Data format for response."
    },
    "quotaUser": {
      "description": "Available to use for quota purposes for server-side applications. Can be any arbitrary string assigned to a user, but should not exceed 40 characters.",
      "type": "string",
      "location": "query"
    }
  },
  "protocol": "rest",
  "basePath": "",
  "id": "firebaseappdistribution:v1alpha"
}
