{
  "version": "v1alpha1",
  "icons": {
    "x32": "http://www.google.com/images/icons/product/search-32.gif",
    "x16": "http://www.google.com/images/icons/product/search-16.gif"
  },
  "mtlsRootUrl": "https://run.mtls.googleapis.com/",
  "batchPath": "batch",
  "ownerDomain": "google.com",
  "discoveryVersion": "v1",
  "name": "run",
  "baseUrl": "https://run.googleapis.com/",
  "fullyEncodeReservedExpansion": true,
  "rootUrl": "https://run.googleapis.com/",
  "documentationLink": "https://cloud.google.com/run/",
  "servicePath": "",
  "kind": "discovery#restDescription",
  "protocol": "rest",
  "resources": {
    "namespaces": {
      "resources": {
        "jobs": {
          "methods": {
            "delete": {
              "parameterOrder": [
                "name"
              ],
              "flatPath": "apis/run.googleapis.com/v1alpha1/namespaces/{namespacesId}/jobs/{jobsId}",
              "scopes": [
                "https://www.googleapis.com/auth/cloud-platform"
              ],
              "parameters": {
                "kind": {
                  "type": "string",
                  "location": "query",
                  "description": "Optional. Cloud Run currently ignores this parameter."
                },
                "name": {
                  "location": "path",
                  "required": true,
                  "pattern": "^namespaces/[^/]+/jobs/[^/]+$",
                  "description": "Required. The name of the job to delete. For Cloud Run (fully managed), replace {namespace_id} with the project ID or number.",
                  "type": "string"
                },
                "apiVersion": {
                  "description": "Optional. Cloud Run currently ignores this parameter.",
                  "type": "string",
                  "location": "query"
                },
                "propagationPolicy": {
                  "location": "query",
                  "description": "Optional. Specifies the propagation policy of delete. Cloud Run currently ignores this setting, and deletes in the background. Please see kubernetes.io/docs/concepts/workloads/controllers/garbage-collection/ for more information.",
                  "type": "string"
                }
              },
              "description": "Delete a job.",
              "path": "apis/run.googleapis.com/v1alpha1/{+name}",
              "httpMethod": "DELETE",
              "response": {
                "$ref": "Empty"
              },
              "id": "run.namespaces.jobs.delete"
            },
            "create": {
              "scopes": [
                "https://www.googleapis.com/auth/cloud-platform"
              ],
              "httpMethod": "POST",
              "path": "apis/run.googleapis.com/v1alpha1/{+parent}/jobs",
              "parameters": {
                "parent": {
                  "description": "Required. The namespace in which the job should be created. Replace {namespace_id} with the project ID or number.",
                  "pattern": "^namespaces/[^/]+$",
                  "type": "string",
                  "required": true,
                  "location": "path"
                }
              },
              "request": {
                "$ref": "Job"
              },
              "description": "Create a job.",
              "parameterOrder": [
                "parent"
              ],
              "response": {
                "$ref": "Job"
              },
              "flatPath": "apis/run.googleapis.com/v1alpha1/namespaces/{namespacesId}/jobs",
              "id": "run.namespaces.jobs.create"
            },
            "list": {
              "scopes": [
                "https://www.googleapis.com/auth/cloud-platform"
              ],
              "parameterOrder": [
                "parent"
              ],
              "path": "apis/run.googleapis.com/v1alpha1/{+parent}/jobs",
              "id": "run.namespaces.jobs.list",
              "flatPath": "apis/run.googleapis.com/v1alpha1/namespaces/{namespacesId}/jobs",
              "httpMethod": "GET",
              "parameters": {
                "fieldSelector": {
                  "type": "string",
                  "description": "Optional. Allows to filter resources based on a specific value for a field name. Send this in a query string format. i.e. 'metadata.name%3Dlorem'. Not currently used by Cloud Run.",
                  "location": "query"
                },
                "watch": {
                  "description": "Optional. Flag that indicates that the client expects to watch this resource as well. Not currently used by Cloud Run.",
                  "location": "query",
                  "type": "boolean"
                },
                "parent": {
                  "type": "string",
                  "pattern": "^namespaces/[^/]+$",
                  "description": "Required. The namespace from which the jobs should be listed. Replace {namespace_id} with the project ID or number.",
                  "required": true,
                  "location": "path"
                },
                "continue": {
                  "description": "Optional. Optional encoded string to continue paging.",
                  "type": "string",
                  "location": "query"
                },
                "limit": {
                  "description": "Optional. The maximum number of records that should be returned.",
                  "format": "int32",
                  "location": "query",
                  "type": "integer"
                },
                "resourceVersion": {
                  "type": "string",
                  "location": "query",
                  "description": "Optional. The baseline resource version from which the list or watch operation should start. Not currently used by Cloud Run."
                },
                "includeUninitialized": {
                  "description": "Optional. Not currently used by Cloud Run.",
                  "location": "query",
                  "type": "boolean"
                },
                "labelSelector": {
                  "description": "Optional. Allows to filter resources based on a label. Supported operations are =, !=, exists, in, and notIn.",
                  "type": "string",
                  "location": "query"
                }
              },
              "response": {
                "$ref": "ListJobsResponse"
              },
              "description": "List jobs."
            },
            "get": {
              "scopes": [
                "https://www.googleapis.com/auth/cloud-platform"
              ],
              "path": "apis/run.googleapis.com/v1alpha1/{+name}",
              "parameters": {
                "name": {
                  "required": true,
                  "description": "Required. The name of the job to retrieve. For Cloud Run (fully managed), replace {namespace_id} with the project ID or number.",
                  "pattern": "^namespaces/[^/]+/jobs/[^/]+$",
                  "type": "string",
                  "location": "path"
                }
              },
              "parameterOrder": [
                "name"
              ],
              "response": {
                "$ref": "Job"
              },
              "httpMethod": "GET",
              "id": "run.namespaces.jobs.get",
              "flatPath": "apis/run.googleapis.com/v1alpha1/namespaces/{namespacesId}/jobs/{jobsId}",
              "description": "Get information about a job."
            }
          }
        }
      }
    }
  },
  "schemas": {
    "ConfigMapEnvSource": {
      "description": "Not supported by Cloud Run ConfigMapEnvSource selects a ConfigMap to populate the environment variables with. The contents of the target ConfigMap's Data field will represent the key-value pairs as environment variables.",
      "properties": {
        "name": {
          "type": "string",
          "description": "The ConfigMap to select from."
        },
        "optional": {
          "description": "(Optional) Specify whether the ConfigMap must be defined",
          "type": "boolean"
        },
        "localObjectReference": {
          "$ref": "LocalObjectReference",
          "description": "This field should not be used directly as it is meant to be inlined directly into the message. Use the \"name\" field instead."
        }
      },
      "type": "object",
      "id": "ConfigMapEnvSource"
    },
    "HTTPGetAction": {
      "type": "object",
      "properties": {
        "path": {
          "type": "string",
          "description": "(Optional) Path to access on the HTTP server."
        },
        "httpHeaders": {
          "description": "(Optional) Custom headers to set in the request. HTTP allows repeated headers.",
          "type": "array",
          "items": {
            "$ref": "HTTPHeader"
          }
        },
        "host": {
          "type": "string",
          "description": "(Optional) Host name to connect to, defaults to the pod IP. You probably want to set \"Host\" in httpHeaders instead."
        },
        "scheme": {
          "type": "string",
          "description": "(Optional) Scheme to use for connecting to the host. Defaults to HTTP."
        }
      },
      "id": "HTTPGetAction",
      "description": "Not supported by Cloud Run HTTPGetAction describes an action based on HTTP Get requests."
    },
    "EnvFromSource": {
      "id": "EnvFromSource",
      "type": "object",
      "description": "Not supported by Cloud Run EnvFromSource represents the source of a set of ConfigMaps",
      "properties": {
        "configMapRef": {
          "$ref": "ConfigMapEnvSource",
          "description": "(Optional) The ConfigMap to select from"
        },
        "secretRef": {
          "description": "(Optional) The Secret to select from",
          "$ref": "SecretEnvSource"
        },
        "prefix": {
          "type": "string",
          "description": "(Optional) An optional identifier to prepend to each key in the ConfigMap. Must be a C_IDENTIFIER."
        }
      }
    },
    "InstanceStatus": {
      "id": "InstanceStatus",
      "description": "Instance represents the status of an instance of a Job.",
      "type": "object",
      "properties": {
        "lastAttemptResult": {
          "description": "Optional. Result of the last attempt of this instance. +optional",
          "$ref": "InstanceAttemptResult"
        },
        "failed": {
          "format": "int32",
          "type": "integer",
          "description": "Optional. The number of times this instance exited with code \u003e 0; +optional"
        },
        "completionTime": {
          "type": "string",
          "description": "Optional. Represents time when the instance was completed. It is not guaranteed to be set in happens-before order across separate operations. It is represented in RFC3339 form and is in UTC. +optional",
          "format": "google-datetime"
        },
        "restarted": {
          "description": "Optional. The number of times this instance was restarted. Instances are restarted according the restartPolicy configured in the Job template. +optional",
          "type": "integer",
          "format": "int32"
        },
        "index": {
          "format": "int32",
          "description": "Required. Index of the instance, unique per Job, and beginning at 0.",
          "type": "integer"
        },
        "startTime": {
          "format": "google-datetime",
          "description": "Optional. Represents time when the instance was created by the job controller. It is not guaranteed to be set in happens-before order across separate operations. It is represented in RFC3339 form and is in UTC. +optional",
          "type": "string"
        },
        "lastExitCode": {
          "format": "int32",
          "description": "Optional. Last exit code seen for this instance. +optional",
          "type": "integer"
        },
        "succeeded": {
          "description": "Optional. The number of times this instance exited with code == 0. +optional",
          "type": "integer",
          "format": "int32"
        }
      }
    },
    "LocalObjectReference": {
      "type": "object",
      "description": "Not supported by Cloud Run LocalObjectReference contains enough information to let you locate the referenced object inside the same namespace.",
      "properties": {
        "name": {
          "type": "string",
          "description": "(Optional) Name of the referent. More info: https://kubernetes.io/docs/concepts/overview/working-with-objects/names/#names"
        }
      },
      "id": "LocalObjectReference"
    },
    "GoogleRpcStatus": {
      "description": "The `Status` type defines a logical error model that is suitable for different programming environments, including REST APIs and RPC APIs. It is used by [gRPC](https://github.com/grpc). Each `Status` message contains three pieces of data: error code, error message, and error details. You can find out more about this error model and how to work with it in the [API Design Guide](https://cloud.google.com/apis/design/errors).",
      "properties": {
        "message": {
          "type": "string",
          "description": "A developer-facing error message, which should be in English. Any user-facing error message should be localized and sent in the google.rpc.Status.details field, or localized by the client."
        },
        "code": {
          "type": "integer",
          "description": "The status code, which should be an enum value of google.rpc.Code.",
          "format": "int32"
        },
        "details": {
          "description": "A list of messages that carry the error details. There is a common set of message types for APIs to use.",
          "items": {
            "type": "object",
            "additionalProperties": {
              "type": "any",
              "description": "Properties of the object. Contains field @type with type URL."
            }
          },
          "type": "array"
        }
      },
      "id": "GoogleRpcStatus",
      "type": "object"
    },
    "ResourceRequirements": {
      "id": "ResourceRequirements",
      "properties": {
        "requests": {
          "type": "object",
          "description": "(Optional) Only memory and CPU are supported. Requests describes the minimum amount of compute resources required. If Requests is omitted for a container, it defaults to Limits if that is explicitly specified, otherwise to an implementation-defined value. The values of the map is string form of the 'quantity' k8s type: https://github.com/kubernetes/kubernetes/blob/master/staging/src/k8s.io/apimachinery/pkg/api/resource/quantity.go",
          "additionalProperties": {
            "type": "string"
          }
        },
        "limits": {
          "type": "object",
          "description": "(Optional) Only memory and CPU are supported. Limits describes the maximum amount of compute resources allowed. The values of the map is string form of the 'quantity' k8s type: https://github.com/kubernetes/kubernetes/blob/master/staging/src/k8s.io/apimachinery/pkg/api/resource/quantity.go",
          "additionalProperties": {
            "type": "string"
          }
        }
      },
      "type": "object",
      "description": "ResourceRequirements describes the compute resource requirements."
    },
    "ObjectMeta": {
      "properties": {
        "labels": {
          "description": "(Optional) Map of string keys and values that can be used to organize and categorize (scope and select) objects. May match selectors of replication controllers and routes. More info: https://kubernetes.io/docs/user-guide/labels",
          "additionalProperties": {
            "type": "string"
          },
          "type": "object"
        },
        "namespace": {
          "description": "Namespace defines the space within each name must be unique, within a Cloud Run region. In Cloud Run the namespace must be equal to either the project ID or project number.",
          "type": "string"
        },
        "uid": {
          "description": "(Optional) UID is the unique in time and space value for this object. It is typically generated by the server on successful creation of a resource and is not allowed to change on PUT operations. Populated by the system. Read-only. More info: https://kubernetes.io/docs/user-guide/identifiers#uids",
          "type": "string"
        },
        "name": {
          "type": "string",
          "description": "Name must be unique within a namespace, within a Cloud Run region. Is required when creating resources, although some resources may allow a client to request the generation of an appropriate name automatically. Name is primarily intended for creation idempotence and configuration definition. Cannot be updated. More info: https://kubernetes.io/docs/user-guide/identifiers#names +optional"
        },
        "annotations": {
          "additionalProperties": {
            "type": "string"
          },
          "type": "object",
          "description": "(Optional) Annotations is an unstructured key value map stored with a resource that may be set by external tools to store and retrieve arbitrary metadata. They are not queryable and should be preserved when modifying objects. More info: https://kubernetes.io/docs/user-guide/annotations"
        },
        "ownerReferences": {
          "description": "(Optional) Not supported by Cloud Run List of objects that own this object. If ALL objects in the list have been deleted, this object will be garbage collected.",
          "items": {
            "$ref": "OwnerReference"
          },
          "type": "array"
        },
        "generation": {
          "description": "(Optional) A sequence number representing a specific generation of the desired state. Populated by the system. Read-only.",
          "format": "int32",
          "type": "integer"
        },
        "clusterName": {
          "type": "string",
          "description": "(Optional) Not supported by Cloud Run The name of the cluster which the object belongs to. This is used to distinguish resources with same name and namespace in different clusters. This field is not set anywhere right now and apiserver is going to ignore it if set in create or update request."
        },
        "generateName": {
          "type": "string",
          "description": "(Optional) Not supported by Cloud Run GenerateName is an optional prefix, used by the server, to generate a unique name ONLY IF the Name field has not been provided. If this field is used, the name returned to the client will be different than the name passed. This value will also be combined with a unique suffix. The provided value has the same validation rules as the Name field, and may be truncated by the length of the suffix required to make the value unique on the server. If this field is specified and the generated name exists, the server will NOT return a 409 - instead, it will either return 201 Created or 500 with Reason ServerTimeout indicating a unique name could not be found in the time allotted, and the client should retry (optionally after the time indicated in the Retry-After header). Applied only if Name is not specified. More info: https://git.k8s.io/community/contributors/devel/api-conventions.md#idempotency string generateName = 2;"
        },
        "deletionTimestamp": {
          "type": "string",
          "description": "(Optional) Not supported by Cloud Run DeletionTimestamp is RFC 3339 date and time at which this resource will be deleted. This field is set by the server when a graceful deletion is requested by the user, and is not directly settable by a client. The resource is expected to be deleted (no longer visible from resource lists, and not reachable by name) after the time in this field, once the finalizers list is empty. As long as the finalizers list contains items, deletion is blocked. Once the deletionTimestamp is set, this value may not be unset or be set further into the future, although it may be shortened or the resource may be deleted prior to this time. For example, a user may request that a pod is deleted in 30 seconds. The Kubelet will react by sending a graceful termination signal to the containers in the pod. After that 30 seconds, the Kubelet will send a hard termination signal (SIGKILL) to the container and after cleanup, remove the pod from the API. In the presence of network partitions, this object may still exist after this timestamp, until an administrator or automated process can determine the resource is fully terminated. If not set, graceful deletion of the object has not been requested. Populated by the system when a graceful deletion is requested. Read-only. More info: https://git.k8s.io/community/contributors/devel/api-conventions.md#metadata",
          "format": "google-datetime"
        },
        "deletionGracePeriodSeconds": {
          "format": "int32",
          "description": "(Optional) Not supported by Cloud Run Number of seconds allowed for this object to gracefully terminate before it will be removed from the system. Only set when deletionTimestamp is also set. May only be shortened. Read-only.",
          "type": "integer"
        },
        "creationTimestamp": {
          "description": "(Optional) CreationTimestamp is a timestamp representing the server time when this object was created. It is not guaranteed to be set in happens-before order across separate operations. Clients may not set this value. It is represented in RFC3339 form and is in UTC. Populated by the system. Read-only. Null for lists. More info: https://git.k8s.io/community/contributors/devel/api-conventions.md#metadata",
          "format": "google-datetime",
          "type": "string"
        },
        "resourceVersion": {
          "type": "string",
          "description": "Optional. An opaque value that represents the internal version of this object that can be used by clients to determine when objects have changed. May be used for optimistic concurrency, change detection, and the watch operation on a resource or set of resources. Clients must treat these values as opaque and passed unmodified back to the server or omit the value to disable conflict-detection. They may only be valid for a particular resource or set of resources. Populated by the system. Read-only. Value must be treated as opaque by clients or omitted. More info: https://git.k8s.io/community/contributors/devel/sig-architecture/api-conventions.md#concurrency-control-and-consistency"
        },
        "selfLink": {
          "description": "(Optional) SelfLink is a URL representing this object. Populated by the system. Read-only. string selfLink = 4;",
          "type": "string"
        },
        "finalizers": {
          "description": "(Optional) Not supported by Cloud Run Must be empty before the object is deleted from the registry. Each entry is an identifier for the responsible component that will remove the entry from the list. If the deletionTimestamp of the object is non-nil, entries in this list can only be removed. +patchStrategy=merge",
          "type": "array",
          "items": {
            "type": "string"
          }
        }
      },
      "type": "object",
      "description": "k8s.io.apimachinery.pkg.apis.meta.v1.ObjectMeta is metadata that all persisted resources must have, which includes all objects users must create.",
      "id": "ObjectMeta"
    },
    "JobStatus": {
      "type": "object",
      "id": "JobStatus",
      "properties": {
        "failed": {
          "type": "integer",
          "format": "int32",
          "description": "Optional. The number of instances which reached phase Failed. +optional"
        },
        "observedGeneration": {
          "type": "integer",
          "description": "Optional. The 'generation' of the job that was last processed by the controller.",
          "format": "int32"
        },
        "imageDigest": {
          "type": "string",
          "description": "Optional. ImageDigest holds the resolved digest for the image specified within .Spec.Template.Spec.Container.Image. The digest is resolved during the creation of the Job. This field holds the digest value regardless of whether a tag or digest was originally specified in the Container object."
        },
        "instances": {
          "items": {
            "$ref": "InstanceStatus"
          },
          "description": "Optional. Status of completed, failed, and running instances. +optional",
          "type": "array"
        },
        "conditions": {
          "items": {
            "$ref": "JobCondition"
          },
          "type": "array",
          "description": "Optional. The latest available observations of a job's current state. More info: https://kubernetes.io/docs/concepts/workloads/controllers/jobs-run-to-completion/ +optional"
        },
        "startTime": {
          "type": "string",
          "format": "google-datetime",
          "description": "Optional. Represents time when the job was acknowledged by the job controller. It is not guaranteed to be set in happens-before order across separate operations. It is represented in RFC3339 form and is in UTC. +optional"
        },
        "active": {
          "type": "integer",
          "format": "int32",
          "description": "Optional. The number of actively running instances. +optional"
        },
        "succeeded": {
          "description": "Optional. The number of instances which reached phase Succeeded. +optional",
          "format": "int32",
          "type": "integer"
        },
        "completionTime": {
          "type": "string",
          "format": "google-datetime",
          "description": "Optional. Represents time when the job was completed. It is not guaranteed to be set in happens-before order across separate operations. It is represented in RFC3339 form and is in UTC. +optional"
        }
      },
      "description": "JobStatus represents the current state of a Job."
    },
    "ConfigMapKeySelector": {
      "id": "ConfigMapKeySelector",
      "properties": {
        "localObjectReference": {
          "$ref": "LocalObjectReference",
          "description": "This field should not be used directly as it is meant to be inlined directly into the message. Use the \"name\" field instead."
        },
        "key": {
          "type": "string",
          "description": "The key to select."
        },
        "name": {
          "type": "string",
          "description": "The ConfigMap to select from."
        },
        "optional": {
          "description": "(Optional) Specify whether the ConfigMap or its key must be defined",
          "type": "boolean"
        }
      },
      "type": "object",
      "description": "Not supported by Cloud Run Selects a key from a ConfigMap."
    },
    "InstanceSpec": {
      "description": "InstanceSpec is a description of an instance.",
      "type": "object",
      "properties": {
        "serviceAccountName": {
          "type": "string",
          "description": "Optional. Email address of the IAM service account associated with the instance of a Job. The service account represents the identity of the running instance, and determines what permissions the instance has. If not provided, the instance will use the project's default service account. +optional"
        },
        "activeDeadlineSeconds": {
          "format": "int64",
          "type": "string",
          "description": "Optional. Optional duration in seconds the instance may be active relative to StartTime before the system will actively try to mark it failed and kill associated containers. If set to zero, the system will never attempt to kill an instance based on time. Otherwise, value must be a positive integer. +optional"
        },
        "terminationGracePeriodSeconds": {
          "type": "string",
          "description": "Optional. Optional duration in seconds the instance needs to terminate gracefully. Value must be non-negative integer. The value zero indicates delete immediately. The grace period is the duration in seconds after the processes running in the instance are sent a termination signal and the time when the processes are forcibly halted with a kill signal. Set this value longer than the expected cleanup time for your process. +optional",
          "format": "int64"
        },
        "containers": {
          "type": "array",
          "description": "Optional. List of containers belonging to the instance. We disallow a number of fields on this Container. Only a single container may be provided.",
          "items": {
            "$ref": "Container"
          }
        },
        "volumes": {
          "description": "Optional. List of volumes that can be mounted by containers belonging to the instance. More info: https://kubernetes.io/docs/concepts/storage/volumes +optional",
          "type": "array",
          "items": {
            "$ref": "Volume"
          }
        },
        "restartPolicy": {
          "type": "string",
          "description": "Optional. Restart policy for all containers within the instance. Allowed values are: - OnFailure: Instances will always be restarted on failure if the backoffLimit has not been reached. - Never: Instances are never restarted and all failures are permanent. Cannot be used if backoffLimit is set. +optional"
        }
      },
      "id": "InstanceSpec"
    },
    "EnvVar": {
      "description": "EnvVar represents an environment variable present in a Container.",
      "id": "EnvVar",
      "properties": {
        "valueFrom": {
          "description": "(Optional) Source for the environment variable's value. Only supports secret_key_ref. Source for the environment variable's value. Cannot be used if value is not empty.",
          "$ref": "EnvVarSource"
        },
        "value": {
          "description": "(Optional) Variable references $(VAR_NAME) are expanded using the previous defined environment variables in the container and any route environment variables. If a variable cannot be resolved, the reference in the input string will be unchanged. The $(VAR_NAME) syntax can be escaped with a double $$, ie: $$(VAR_NAME). Escaped references will never be expanded, regardless of whether the variable exists or not. Defaults to \"\".",
          "type": "string"
        },
        "name": {
          "description": "Name of the environment variable. Must be a C_IDENTIFIER.",
          "type": "string"
        }
      },
      "type": "object"
    },
    "Probe": {
      "description": "Not supported by Cloud Run Probe describes a health check to be performed against a container to determine whether it is alive or ready to receive traffic.",
      "id": "Probe",
      "properties": {
        "periodSeconds": {
          "type": "integer",
          "description": "(Optional) How often (in seconds) to perform the probe. Default to 10 seconds. Minimum value is 1. Max value for liveness probe is 3600. Max value for startup probe is 240. Must be greater or equal than timeout_seconds.",
          "format": "int32"
        },
        "tcpSocket": {
          "description": "(Optional) TCPSocket specifies an action involving a TCP port. TCP hooks not yet supported A field inlined from the Handler message.",
          "$ref": "TCPSocketAction"
        },
        "initialDelaySeconds": {
          "description": "(Optional) Number of seconds after the container has started before liveness probes are initiated. Defaults to 0 seconds. Minimum value is 0. Max value for liveness probe is 3600. Max value for startup probe is 240. More info: https://kubernetes.io/docs/concepts/workloads/pods/pod-lifecycle#container-probes",
          "format": "int32",
          "type": "integer"
        },
        "successThreshold": {
          "format": "int32",
          "type": "integer",
          "description": "(Optional) Minimum consecutive successes for the probe to be considered successful after having failed. Defaults to 1. Must be 1 for liveness and startup Probes."
        },
        "failureThreshold": {
          "format": "int32",
          "description": "(Optional) Minimum consecutive failures for the probe to be considered failed after having succeeded. Defaults to 3. Minimum value is 1.",
          "type": "integer"
        },
        "grpc": {
          "description": "(Optional) GRPCAction specifies an action involving a GRPC port. A field inlined from the Handler message.",
          "$ref": "GRPCAction"
        },
        "timeoutSeconds": {
          "type": "integer",
          "format": "int32",
          "description": "(Optional) Number of seconds after which the probe times out. Defaults to 1 second. Minimum value is 1. Maximum value is 3600. Must be smaller than period_seconds. More info: https://kubernetes.io/docs/concepts/workloads/pods/pod-lifecycle#container-probes"
        },
        "httpGet": {
          "description": "(Optional) HTTPGet specifies the http request to perform. A field inlined from the Handler message.",
          "$ref": "HTTPGetAction"
        },
        "exec": {
          "$ref": "ExecAction",
          "description": "(Optional) One and only one of the following should be specified. Exec specifies the action to take. A field inlined from the Handler message."
        }
      },
      "type": "object"
    },
    "ExecAction": {
      "type": "object",
      "id": "ExecAction",
      "properties": {
        "command": {
          "type": "array",
          "items": {
            "type": "string"
          },
          "description": "(Optional) Command is the command line to execute inside the container, the working directory for the command is root ('/') in the container's filesystem. The command is simply exec'd, it is not run inside a shell, so traditional shell instructions ('|', etc) won't work. To use a shell, you need to explicitly call out to that shell. Exit status of 0 is treated as live/healthy and non-zero is unhealthy."
        }
      },
      "description": "Not supported by Cloud Run ExecAction describes a \"run in container\" action."
    },
    "EnvVarSource": {
      "properties": {
        "secretKeyRef": {
          "description": "(Optional) Selects a key (version) of a secret in Secret Manager.",
          "$ref": "SecretKeySelector"
        },
        "configMapKeyRef": {
          "$ref": "ConfigMapKeySelector",
          "description": "(Optional) Not supported by Cloud Run Selects a key of a ConfigMap."
        }
      },
      "type": "object",
      "id": "EnvVarSource",
      "description": "EnvVarSource represents a source for the value of an EnvVar."
    },
    "Job": {
      "description": "Job represents the configuration of a single job. A job an immutable resource that references a container image which is run to completion.",
      "type": "object",
      "properties": {
        "apiVersion": {
          "type": "string",
          "description": "Optional. APIVersion defines the versioned schema of this representation of an object. Servers should convert recognized schemas to the latest internal value, and may reject unrecognized values. More info: https://git.k8s.io/community/contributors/devel/sig-architecture/api-conventions.md#resources +optional"
        },
        "kind": {
          "description": "Optional. Kind is a string value representing the REST resource this object represents. Servers may infer this from the endpoint the client submits requests to. Cannot be updated. In CamelCase. More info: https://git.k8s.io/community/contributors/devel/sig-architecture/api-conventions.md#types-kinds +optional",
          "type": "string"
        },
        "spec": {
          "$ref": "JobSpec",
          "description": "Optional. Specification of the desired behavior of a job. More info: https://git.k8s.io/community/contributors/devel/api-conventions.md#spec-and-status +optional"
        },
        "status": {
          "description": "Optional. Current status of a job. More info: https://git.k8s.io/community/contributors/devel/api-conventions.md#spec-and-status +optional",
          "$ref": "JobStatus"
        },
        "metadata": {
          "description": "Optional. Standard object's metadata. More info: https://git.k8s.io/community/contributors/devel/api-conventions.md#metadata +optional",
          "$ref": "ObjectMeta"
        }
      },
      "id": "Job"
    },
    "ContainerPort": {
      "description": "ContainerPort represents a network port in a single container.",
      "type": "object",
      "properties": {
        "protocol": {
          "type": "string",
          "description": "(Optional) Protocol for port. Must be \"TCP\". Defaults to \"TCP\"."
        },
        "containerPort": {
          "description": "(Optional) Port number the container listens on. This must be a valid port number, 0 \u003c x \u003c 65536.",
          "type": "integer",
          "format": "int32"
        },
        "name": {
          "type": "string",
          "description": "(Optional) If specified, used to specify which protocol to use. Allowed values are \"http1\" and \"h2c\"."
        }
      },
      "id": "ContainerPort"
    },
    "KeyToPath": {
      "type": "object",
      "description": "Maps a string key to a path within a volume.",
      "id": "KeyToPath",
      "properties": {
        "mode": {
          "format": "int32",
          "description": "(Optional) Mode bits to use on this file, must be a value between 01 and 0777 (octal). If 0 or not set, the Volume's default mode will be used. Notes * Internally, a umask of 0222 will be applied to any non-zero value. * This is an integer representation of the mode bits. So, the octal integer value should look exactly as the chmod numeric notation with a leading zero. Some examples: for chmod 777 (a=rwx), set to 0777 (octal) or 511 (base-10). For chmod 640 (u=rw,g=r), set to 0640 (octal) or 416 (base-10). For chmod 755 (u=rwx,g=rx,o=rx), set to 0755 (octal) or 493 (base-10). * This might be in conflict with other options that affect the file mode, like fsGroup, and the result can be other mode bits set.",
          "type": "integer"
        },
        "path": {
          "description": "The relative path of the file to map the key to. May not be an absolute path. May not contain the path element '..'. May not start with the string '..'.",
          "type": "string"
        },
        "key": {
          "description": "The Cloud Secret Manager secret version. Can be 'latest' for the latest value or an integer for a specific version. The key to project.",
          "type": "string"
        }
      }
    },
    "Empty": {
      "description": "A generic empty message that you can re-use to avoid defining duplicated empty messages in your APIs. A typical example is to use it as the request or the response type of an API method. For instance: service Foo { rpc Bar(google.protobuf.Empty) returns (google.protobuf.Empty); }",
      "id": "Empty",
      "properties": {},
      "type": "object"
    },
    "InstanceAttemptResult": {
      "description": "Result of an instance attempt.",
      "id": "InstanceAttemptResult",
      "properties": {
        "status": {
          "description": "Optional. The status of this attempt. If the status code is OK, then the attempt succeeded.",
          "$ref": "GoogleRpcStatus"
        },
        "exitCode": {
          "type": "integer",
          "description": "Optional. The exit code of this attempt. This may be unset if the container was unable to exit cleanly with a code due to some other failure. See status field for possible failure details.",
          "format": "int32"
        }
      },
      "type": "object"
    },
    "InstanceTemplateSpec": {
      "id": "InstanceTemplateSpec",
      "type": "object",
      "description": "InstanceTemplateSpec describes the data an instance should have when created from a template.",
      "properties": {
        "spec": {
          "$ref": "InstanceSpec",
          "description": "Optional. Specification of the desired behavior of the instance. More info: https://git.k8s.io/community/contributors/devel/sig-architecture/api-conventions.md#spec-and-status +optional"
        }
      }
    },
    "ConfigMapVolumeSource": {
      "id": "ConfigMapVolumeSource",
      "type": "object",
      "properties": {
        "defaultMode": {
          "format": "int32",
          "type": "integer",
          "description": "(Optional) Integer representation of mode bits to use on created files by default. Must be a value between 01 and 0777 (octal). If 0 or not set, it will default to 0644. Directories within the path are not affected by this setting. Notes * Internally, a umask of 0222 will be applied to any non-zero value. * This is an integer representation of the mode bits. So, the octal integer value should look exactly as the chmod numeric notation with a leading zero. Some examples: for chmod 777 (a=rwx), set to 0777 (octal) or 511 (base-10). For chmod 640 (u=rw,g=r), set to 0640 (octal) or 416 (base-10). For chmod 755 (u=rwx,g=rx,o=rx), set to 0755 (octal) or 493 (base-10). * This might be in conflict with other options that affect the file mode, like fsGroup, and the result can be other mode bits set."
        },
        "name": {
          "type": "string",
          "description": "Name of the config."
        },
        "optional": {
          "description": "(Optional) Specify whether the Secret or its keys must be defined.",
          "type": "boolean"
        },
        "items": {
          "type": "array",
          "items": {
            "$ref": "KeyToPath"
          },
          "description": "(Optional) If unspecified, each key-value pair in the Data field of the referenced Secret will be projected into the volume as a file whose name is the key and content is the value. If specified, the listed keys will be projected into the specified paths, and unlisted keys will not be present. If a key is specified that is not present in the Secret, the volume setup will error unless it is marked optional."
        }
      },
      "description": "Not supported by Cloud Run Adapts a ConfigMap into a volume. The contents of the target ConfigMap's Data field will be presented in a volume as files using the keys in the Data field as the file names, unless the items element is populated with specific mappings of keys to paths."
    },
    "OwnerReference": {
      "description": "OwnerReference contains enough information to let you identify an owning object. Currently, an owning object must be in the same namespace, so there is no namespace field.",
      "type": "object",
      "id": "OwnerReference",
      "properties": {
        "kind": {
          "type": "string",
          "description": "Kind of the referent. More info: https://git.k8s.io/community/contributors/devel/sig-architecture/api-conventions.md#types-kinds"
        },
        "blockOwnerDeletion": {
          "description": "If true, AND if the owner has the \"foregroundDeletion\" finalizer, then the owner cannot be deleted from the key-value store until this reference is removed. Defaults to false. To set this field, a user needs \"delete\" permission of the owner, otherwise 422 (Unprocessable Entity) will be returned. +optional",
          "type": "boolean"
        },
        "controller": {
          "type": "boolean",
          "description": "If true, this reference points to the managing controller. +optional"
        },
        "uid": {
          "description": "UID of the referent. More info: https://kubernetes.io/docs/user-guide/identifiers#uids",
          "type": "string"
        },
        "name": {
          "description": "Name of the referent. More info: https://kubernetes.io/docs/user-guide/identifiers#names",
          "type": "string"
        },
        "apiVersion": {
          "description": "API version of the referent.",
          "type": "string"
        }
      }
    },
    "Container": {
      "properties": {
        "env": {
          "items": {
            "$ref": "EnvVar"
          },
          "description": "(Optional) List of environment variables to set in the container.",
          "type": "array"
        },
        "args": {
          "items": {
            "type": "string"
          },
          "type": "array",
          "description": "(Optional) Arguments to the entrypoint. The docker image's CMD is used if this is not provided. Variable references $(VAR_NAME) are expanded using the container's environment. If a variable cannot be resolved, the reference in the input string will be unchanged. The $(VAR_NAME) syntax can be escaped with a double $$, ie: $$(VAR_NAME). Escaped references will never be expanded, regardless of whether the variable exists or not. More info: https://kubernetes.io/docs/tasks/inject-data-application/define-command-argument-container/#running-a-command-in-a-shell"
        },
        "volumeMounts": {
          "type": "array",
          "description": "(Optional) Volume to mount into the container's filesystem. Only supports SecretVolumeSources. Pod volumes to mount into the container's filesystem.",
          "items": {
            "$ref": "VolumeMount"
          }
        },
        "command": {
          "type": "array",
          "items": {
            "type": "string"
          }
        },
        "resources": {
          "$ref": "ResourceRequirements",
          "description": "(Optional) Compute Resources required by this container. More info: https://kubernetes.io/docs/concepts/storage/persistent-volumes#resources"
        },
        "terminationMessagePath": {
          "description": "(Optional) Path at which the file to which the container's termination message will be written is mounted into the container's filesystem. Message written is intended to be brief final status, such as an assertion failure message. Will be truncated by the node if greater than 4096 bytes. The total message length across all containers will be limited to 12kb. Defaults to /dev/termination-log.",
          "type": "string"
        },
        "envFrom": {
          "type": "array",
          "description": "(Optional) List of sources to populate environment variables in the container. The keys defined within a source must be a C_IDENTIFIER. All invalid keys will be reported as an event when the container is starting. When a key exists in multiple sources, the value associated with the last source will take precedence. Values defined by an Env with a duplicate key will take precedence. Cannot be updated.",
          "items": {
            "$ref": "EnvFromSource"
          }
        },
        "ports": {
          "type": "array",
          "description": "(Optional) List of ports to expose from the container. Only a single port can be specified. The specified ports must be listening on all interfaces (0.0.0.0) within the container to be accessible. If omitted, a port number will be chosen and passed to the container through the PORT environment variable for the container to listen on.",
          "items": {
            "$ref": "ContainerPort"
          }
        },
        "workingDir": {
          "type": "string",
          "description": "(Optional) Container's working directory. If not specified, the container runtime's default will be used, which might be configured in the container image."
        },
        "startupProbe": {
          "$ref": "Probe",
          "description": "(Optional) Startup probe of application within the container. All other probes are disabled if a startup probe is provided, until it succeeds. Container will not be added to service endpoints if the probe fails. More info: https://kubernetes.io/docs/concepts/workloads/pods/pod-lifecycle#container-probes"
        },
        "image": {
          "type": "string",
          "description": "Only supports containers from Google Container Registry or Artifact Registry URL of the Container image. More info: https://kubernetes.io/docs/concepts/containers/images"
        },
        "livenessProbe": {
          "description": "(Optional) Periodic probe of container liveness. Container will be restarted if the probe fails. More info: https://kubernetes.io/docs/concepts/workloads/pods/pod-lifecycle#container-probes",
          "$ref": "Probe"
        },
        "securityContext": {
          "$ref": "SecurityContext",
          "description": "(Optional) Security options the pod should run with. More info: https://kubernetes.io/docs/concepts/policy/security-context/ More info: https://kubernetes.io/docs/tasks/configure-pod-container/security-context/"
        },
        "readinessProbe": {
          "$ref": "Probe",
          "description": "(Optional) Periodic probe of container service readiness. Container will be removed from service endpoints if the probe fails. More info: https://kubernetes.io/docs/concepts/workloads/pods/pod-lifecycle#container-probes"
        },
        "name": {
          "type": "string",
          "description": "(Optional) Name of the container specified as a DNS_LABEL. Currently unused in Cloud Run. More info: https://kubernetes.io/docs/concepts/overview/working-with-objects/names/#dns-label-names"
        },
        "terminationMessagePolicy": {
          "type": "string",
          "description": "(Optional) Indicate how the termination message should be populated. File will use the contents of terminationMessagePath to populate the container status message on both success and failure. FallbackToLogsOnError will use the last chunk of container log output if the termination message file is empty and the container exited with an error. The log output is limited to 2048 bytes or 80 lines, whichever is smaller. Defaults to File. Cannot be updated."
        },
        "imagePullPolicy": {
          "type": "string",
          "description": "(Optional) Image pull policy. One of Always, Never, IfNotPresent. Defaults to Always if :latest tag is specified, or IfNotPresent otherwise. More info: https://kubernetes.io/docs/concepts/containers/images#updating-images"
        }
      },
      "type": "object",
      "description": "A single application container. This specifies both the container to run, the command to run in the container and the arguments to supply to it. Note that additional arguments may be supplied by the system to the container at runtime.",
      "id": "Container"
    },
    "HTTPHeader": {
      "description": "Not supported by Cloud Run HTTPHeader describes a custom header to be used in HTTP probes",
      "id": "HTTPHeader",
      "properties": {
        "name": {
          "description": "The header field name",
          "type": "string"
        },
        "value": {
          "description": "The header field value",
          "type": "string"
        }
      },
      "type": "object"
    },
    "SecretVolumeSource": {
      "type": "object",
      "id": "SecretVolumeSource",
      "description": "The secret's value will be presented as the content of a file whose name is defined in the item path. If no items are defined, the name of the file is the secret_name. The contents of the target Secret's Data field will be presented in a volume as files using the keys in the Data field as the file names.",
      "properties": {
        "secretName": {
          "type": "string",
          "description": "The name of the secret in Cloud Secret Manager. By default, the secret is assumed to be in the same project. If the secret is in another project, you must define an alias. An alias definition has the form: :projects//secrets/. If multiple alias definitions are needed, they must be separated by commas. The alias definitions must be set on the run.googleapis.com/secrets annotation. Name of the secret in the container's namespace to use."
        },
        "defaultMode": {
          "format": "int32",
          "description": "Integer representation of mode bits to use on created files by default. Must be a value between 01 and 0777 (octal). If 0 or not set, it will default to 0644. Directories within the path are not affected by this setting. Notes * Internally, a umask of 0222 will be applied to any non-zero value. * This is an integer representation of the mode bits. So, the octal integer value should look exactly as the chmod numeric notation with a leading zero. Some examples: for chmod 777 (a=rwx), set to 0777 (octal) or 511 (base-10). For chmod 640 (u=rw,g=r), set to 0640 (octal) or 416 (base-10). For chmod 755 (u=rwx,g=rx,o=rx), set to 0755 (octal) or 493 (base-10). * This might be in conflict with other options that affect the file mode, like fsGroup, and the result can be other mode bits set.",
          "type": "integer"
        },
        "optional": {
          "type": "boolean",
          "description": "(Optional) Specify whether the Secret or its keys must be defined."
        },
        "items": {
          "items": {
            "$ref": "KeyToPath"
          },
          "type": "array",
          "description": "(Optional) If unspecified, the volume will expose a file whose name is the secret_name. If specified, the key will be used as the version to fetch from Cloud Secret Manager and the path will be the name of the file exposed in the volume. When items are defined, they must specify a key and a path. If unspecified, each key-value pair in the Data field of the referenced Secret will be projected into the volume as a file whose name is the key and content is the value. If specified, the listed keys will be projected into the specified paths, and unlisted keys will not be present. If a key is specified that is not present in the Secret, the volume setup will error unless it is marked optional."
        }
      }
    },
    "SecurityContext": {
      "type": "object",
      "properties": {
        "runAsUser": {
          "format": "int32",
          "type": "integer",
          "description": "(Optional) The UID to run the entrypoint of the container process. Defaults to user specified in image metadata if unspecified. May also be set in PodSecurityContext. If set in both SecurityContext and PodSecurityContext, the value specified in SecurityContext takes precedence."
        }
      },
      "description": "Not supported by Cloud Run SecurityContext holds security configuration that will be applied to a container. Some fields are present in both SecurityContext and PodSecurityContext. When both are set, the values in SecurityContext take precedence.",
      "id": "SecurityContext"
    },
    "TCPSocketAction": {
      "properties": {
        "port": {
          "description": "Number or name of the port to access on the container. Number must be in the range 1 to 65535. Name must be an IANA_SVC_NAME. This field is currently limited to integer types only because of proto's inability to properly support the IntOrString golang type.",
          "format": "int32",
          "type": "integer"
        },
        "host": {
          "type": "string",
          "description": "(Optional) Optional: Host name to connect to, defaults to the pod IP."
        }
      },
      "description": "Not supported by Cloud Run TCPSocketAction describes an action based on opening a socket",
      "id": "TCPSocketAction",
      "type": "object"
    },
    "ListJobsResponse": {
      "properties": {
        "apiVersion": {
          "type": "string",
          "description": "The API version for this call such as \"run.googleapis.com/v1alpha1\"."
        },
        "nextPageToken": {
          "type": "string",
          "description": "This field is equivalent to the metadata.continue field and is provided as a convenience for compatibility with https://google.aip.dev/158. The value is opaque and may be used to issue another request to the endpoint that served this list to retrieve the next set of available objects. Continuing a list may not be possible if the server configuration has changed or more than a few minutes have passed. The metadata.resourceVersion field returned when using this field will be identical to the value in the first response."
        },
        "kind": {
          "description": "The kind of this resource, in this case \"JobsList\".",
          "type": "string"
        },
        "unreachable": {
          "description": "Locations that could not be reached.",
          "items": {
            "type": "string"
          },
          "type": "array"
        },
        "items": {
          "type": "array",
          "items": {
            "$ref": "Job"
          },
          "description": "List of Jobs."
        },
        "metadata": {
          "$ref": "ListMeta",
          "description": "Metadata associated with this jobs list."
        }
      },
      "description": "ListJobsResponse is a list of Jobs resources.",
      "type": "object",
      "id": "ListJobsResponse"
    },
    "JobSpec": {
      "type": "object",
      "properties": {
        "template": {
          "description": "Optional. Describes the instance that will be created when executing a job.",
          "$ref": "InstanceTemplateSpec"
        },
        "ttlSecondsAfterFinished": {
          "format": "int32",
          "description": "Optional. Not supported. ttlSecondsAfterFinished limits the lifetime of a Job that has finished execution (either Complete or Failed). If this field is set, ttlSecondsAfterFinished after the Job finishes, it is eligible to be automatically deleted. When the Job is being deleted, its lifecycle guarantees (e.g. finalizers) will be honored. If this field is set to zero, the Job won't be automatically deleted. +optional",
          "type": "integer"
        },
        "backoffLimit": {
          "type": "integer",
          "format": "int32",
          "description": "Optional. Specifies the number of retries per instance, before marking this job failed. If set to zero, instances will never retry on failure. +optional"
        },
        "parallelism": {
          "format": "int32",
          "type": "integer",
          "description": "Optional. Specifies the maximum desired number of instances the job should run at any given time. Must be \u003c= completions. The actual number of instances running in steady state will be less than this number when ((.spec.completions - .status.successful) \u003c .spec.parallelism), i.e. when the work left to do is less than max parallelism. More info: https://kubernetes.io/docs/concepts/workloads/controllers/jobs-run-to-completion/ +optional"
        },
        "activeDeadlineSeconds": {
          "description": "Optional. Not supported. Specifies the duration in seconds relative to the startTime that the job may be active before the system tries to terminate it. If set to zero, the system will never attempt to terminate the job based on time. Otherwise, the value must be positive integer. +optional",
          "type": "string",
          "format": "int64"
        },
        "completions": {
          "description": "Optional. Specifies the desired number of successfully finished instances the job should be run with. Setting to 1 means that parallelism is limited to 1 and the success of that instance signals the success of the job. More info: https://kubernetes.io/docs/concepts/workloads/controllers/jobs-run-to-completion/ +optional",
          "type": "integer",
          "format": "int32"
        }
      },
      "description": "JobSpec describes how the job execution will look like.",
      "id": "JobSpec"
    },
    "GRPCAction": {
      "description": "Not supported by Cloud Run GRPCAction describes an action involving a GRPC port.",
      "type": "object",
      "id": "GRPCAction",
      "properties": {
        "service": {
          "description": "Service is the name of the service to place in the gRPC HealthCheckRequest (see https://github.com/grpc/grpc/blob/master/doc/health-checking.md). If this is not specified, the default behavior is defined by gRPC.",
          "type": "string"
        },
        "port": {
          "type": "integer",
          "format": "int32",
          "description": "Port number of the gRPC service. Number must be in the range 1 to 65535."
        }
      }
    },
    "JobCondition": {
      "id": "JobCondition",
      "description": "JobCondition defines a readiness condition for a Revision.",
      "type": "object",
      "properties": {
        "message": {
          "type": "string",
          "description": "Optional. Human readable message indicating details about the current status."
        },
        "reason": {
          "description": "Optional. One-word CamelCase reason for the condition's last transition.",
          "type": "string"
        },
        "severity": {
          "type": "string",
          "description": "Optional. How to interpret failures of this condition, one of Error, Warning, Info"
        },
        "type": {
          "type": "string",
          "description": "Required. Type is used to communicate the status of the reconciliation process. See also: https://github.com/knative/serving/blob/main/docs/spec/errors.md#error-conditions-and-reporting Types include: * \"Completed\": True when the Job has successfully completed. * \"Started\": True when the Job has successfully started running. * \"ResourcesAvailable\": True when underlying resources have been provisioned."
        },
        "lastTransitionTime": {
          "format": "google-datetime",
          "type": "string",
          "description": "Optional. Last time the condition transitioned from one status to another."
        },
        "status": {
          "type": "string",
          "description": "Required. Status of the condition, one of True, False, Unknown."
        }
      }
    },
    "SecretKeySelector": {
      "properties": {
        "name": {
          "type": "string",
          "description": "The name of the secret in Cloud Secret Manager. By default, the secret is assumed to be in the same project. If the secret is in another project, you must define an alias. An alias definition has the form: :projects//secrets/. If multiple alias definitions are needed, they must be separated by commas. The alias definitions must be set on the run.googleapis.com/secrets annotation. The name of the secret in the pod's namespace to select from."
        },
        "localObjectReference": {
          "$ref": "LocalObjectReference",
          "description": "This field should not be used directly as it is meant to be inlined directly into the message. Use the \"name\" field instead."
        },
        "key": {
          "description": "A Cloud Secret Manager secret version. Must be 'latest' for the latest version or an integer for a specific version. The key of the secret to select from. Must be a valid secret key.",
          "type": "string"
        },
        "optional": {
          "type": "boolean",
          "description": "(Optional) Specify whether the Secret or its key must be defined"
        }
      },
      "type": "object",
      "id": "SecretKeySelector",
      "description": "SecretKeySelector selects a key of a Secret."
    },
    "SecretEnvSource": {
      "description": "Not supported by Cloud Run SecretEnvSource selects a Secret to populate the environment variables with. The contents of the target Secret's Data field will represent the key-value pairs as environment variables.",
      "id": "SecretEnvSource",
      "properties": {
        "name": {
          "description": "The Secret to select from.",
          "type": "string"
        },
        "localObjectReference": {
          "$ref": "LocalObjectReference",
          "description": "This field should not be used directly as it is meant to be inlined directly into the message. Use the \"name\" field instead."
        },
        "optional": {
          "description": "(Optional) Specify whether the Secret must be defined",
          "type": "boolean"
        }
      },
      "type": "object"
    },
    "ListMeta": {
      "properties": {
        "resourceVersion": {
          "description": "String that identifies the server's internal version of this object that can be used by clients to determine when objects have changed. Value must be treated as opaque by clients and passed unmodified back to the server. Populated by the system. Read-only. More info: https://git.k8s.io/community/contributors/devel/api-conventions.md#concurrency-control-and-consistency +optional",
          "type": "string"
        },
        "selfLink": {
          "description": "SelfLink is a URL representing this object. Populated by the system. Read-only. +optional",
          "type": "string"
        },
        "continue": {
          "description": "continue may be set if the user set a limit on the number of items returned, and indicates that the server has more data available. The value is opaque and may be used to issue another request to the endpoint that served this list to retrieve the next set of available objects. Continuing a list may not be possible if the server configuration has changed or more than a few minutes have passed. The resourceVersion field returned when using this continue value will be identical to the value in the first response.",
          "type": "string"
        }
      },
      "type": "object",
      "id": "ListMeta",
      "description": "ListMeta describes metadata that synthetic resources must have, including lists and various status objects. A resource may have only one of {ObjectMeta, ListMeta}."
    },
    "Volume": {
      "properties": {
        "secret": {
          "$ref": "SecretVolumeSource"
        },
        "name": {
          "type": "string",
          "description": "Volume's name. In Cloud Run Fully Managed, the name 'cloudsql' is reserved."
        },
        "configMap": {
          "$ref": "ConfigMapVolumeSource"
        }
      },
      "description": "Volume represents a named volume in a container.",
      "id": "Volume",
      "type": "object"
    },
    "VolumeMount": {
      "properties": {
        "mountPath": {
          "type": "string",
          "description": "Path within the container at which the volume should be mounted. Must not contain ':'."
        },
        "subPath": {
          "type": "string",
          "description": "(Optional) Path within the volume from which the container's volume should be mounted. Defaults to \"\" (volume's root)."
        },
        "readOnly": {
          "description": "(Optional) Only true is accepted. Defaults to true.",
          "type": "boolean"
        },
        "name": {
          "description": "The name of the volume. There must be a corresponding Volume with the same name.",
          "type": "string"
        }
      },
      "id": "VolumeMount",
      "type": "object",
      "description": "VolumeMount describes a mounting of a Volume within a container."
    }
  },
  "auth": {
    "oauth2": {
      "scopes": {
        "https://www.googleapis.com/auth/cloud-platform": {
          "description": "See, edit, configure, and delete your Google Cloud data and see the email address for your Google Account."
        }
      }
    }
  },
  "id": "run:v1alpha1",
  "parameters": {
    "prettyPrint": {
      "type": "boolean",
      "default": "true",
      "location": "query",
      "description": "Returns response with indentations and line breaks."
    },
    "quotaUser": {
      "description": "Available to use for quota purposes for server-side applications. Can be any arbitrary string assigned to a user, but should not exceed 40 characters.",
      "type": "string",
      "location": "query"
    },
    "upload_protocol": {
      "type": "string",
      "location": "query",
      "description": "Upload protocol for media (e.g. \"raw\", \"multipart\")."
    },
    "key": {
      "location": "query",
      "type": "string",
      "description": "API key. Your API key identifies your project and provides you with API access, quota, and reports. Required unless you provide an OAuth 2.0 token."
    },
    "oauth_token": {
      "location": "query",
      "description": "OAuth 2.0 token for the current user.",
      "type": "string"
    },
    "alt": {
      "type": "string",
      "location": "query",
      "default": "json",
      "enumDescriptions": [
        "Responses with Content-Type of application/json",
        "Media download with context-dependent Content-Type",
        "Responses with Content-Type of application/x-protobuf"
      ],
      "enum": [
        "json",
        "media",
        "proto"
      ],
      "description": "Data format for response."
    },
    "uploadType": {
      "location": "query",
      "description": "Legacy upload protocol for media (e.g. \"media\", \"multipart\").",
      "type": "string"
    },
    "access_token": {
      "location": "query",
      "type": "string",
      "description": "OAuth access token."
    },
    "callback": {
      "description": "JSONP",
      "type": "string",
      "location": "query"
    },
    "$.xgafv": {
      "type": "string",
      "enumDescriptions": [
        "v1 error format",
        "v2 error format"
      ],
      "enum": [
        "1",
        "2"
      ],
      "description": "V1 error format.",
      "location": "query"
    },
    "fields": {
      "type": "string",
      "location": "query",
      "description": "Selector specifying which fields to include in a partial response."
    }
  },
  "title": "Cloud Run Admin API",
  "description": "Deploy and manage user provided container images that scale automatically based on incoming requests. The Cloud Run Admin API v1 follows the Knative Serving API specification, while v2 is aligned with Google Cloud AIP-based API standards, as described in https://google.aip.dev/.",
  "version_module": true,
  "revision": "20220429",
  "ownerName": "Google",
  "canonicalName": "Cloud Run",
  "basePath": ""
}
